CHANGES.txt
README.txt
TODO.txt
setup.py
zopeskel/__init__.py
zopeskel.doctools.egg-info/PKG-INFO
zopeskel.doctools.egg-info/SOURCES.txt
zopeskel.doctools.egg-info/dependency_links.txt
zopeskel.doctools.egg-info/entry_points.txt
zopeskel.doctools.egg-info/namespace_packages.txt
zopeskel.doctools.egg-info/requires.txt
zopeskel.doctools.egg-info/top_level.txt
zopeskel.doctools.egg-info/zip-safe
zopeskel/doctools/__init__.py
zopeskel/doctools/graph.py
zopeskel/doctools/html_doc.py