Metadata-Version: 1.0
Name: zopeskel.doctools
Version: 1.0
Summary: Tools for documenting ZopeSkel.
Home-page: UNKNOWN
Author: Joel Burton, Cris Ewing, Chris Calloway
Author-email: cbc@chriscalloway.org
License: MIT
Keywords: web skeleton project Plone Zope ZopeSkel Paster GraphViz
Platform: UNKNOWN
Classifier: Development Status :: 5 - Production/Stable
Classifier: Framework :: Zope2
Classifier: Framework :: Zope3
Classifier: Framework :: Plone
Classifier: Intended Audience :: Developers
Classifier: License :: OSI Approved :: MIT License
Classifier: Programming Language :: Python
Classifier: Topic :: Internet :: WWW/HTTP
Classifier: Topic :: Internet :: WWW/HTTP :: Dynamic Content
Classifier: Topic :: Software Development :: Documentation
